pnp_datetime/__init__.py
pnp_datetime/pnp_datetime.py
pnp_datetime-0.7.0.dist-info/LICENSE
pnp_datetime-0.7.0.dist-info/METADATA
pnp_datetime-0.7.0.dist-info/WHEEL
pnp_datetime-0.7.0.dist-info/top_level.txt
pnp_datetime-0.7.0.dist-info/RECORD
