Metadata-Version: 2.1
Name: pnp-datetime
Version: 0.7.0
Summary: Python Plug and Play style datetime
Home-page: https://github.com/pypnp/pnp_datetime
Author: PyPnP
Author-email: pypnp@protonmail.com
License: UNKNOWN
Platform: UNKNOWN
Classifier: Programming Language :: Python :: 3
Classifier: License :: OSI Approved :: MIT License
Classifier: Operating System :: OS Independent
Requires-Python: >=3.6
